fa_scraper/__init__.py
fa_scraper/cli.py
fa_scraper/fa_scraper.py
fa_scraper/types.py
fa_scraper-0.4.1.dist-info/AUTHORS
fa_scraper-0.4.1.dist-info/LICENSE
fa_scraper-0.4.1.dist-info/METADATA
fa_scraper-0.4.1.dist-info/WHEEL
fa_scraper-0.4.1.dist-info/entry_points.txt
fa_scraper-0.4.1.dist-info/RECORD
