Metadata-Version: 2.3
Name: fa-scraper
Version: 0.4.1
Summary: A Letterboxd-compatible FilmAffinity scraper.
License: GPL-3.0-or-later
Author: Pablo Baeyens
Author-email: pbaeyens31+github@gmail.com
Requires-Python: >=3.9
Classifier: Development Status :: 4 - Beta
Classifier: Intended Audience :: End Users/Desktop
Classifier: Natural Language :: English
Classifier: Operating System :: OS Independent
Classifier: Topic :: Utilities
Classifier: Environment :: Console
Requires-Dist: arrow (>=1.2.1,<2.0)
Requires-Dist: beautifulsoup4 (>=4.9.1,<5.0)
Requires-Dist: lxml (>=4.5.1,<6.0.0)
Requires-Dist: requests (>=2.21.0,<3.0)
Project-URL: Repository, https://github.com/mx-psi/fa-scraper
Project-URL: authors, https://github.com/mx-psi/fa-scraper/blob/main/AUTHORS
Project-URL: changelog, https://github.com/mx-psi/fa-scraper/blob/main/CHANGELOG.md
Project-URL: issues, https://github.com/mx-psi/fa-scraper/issues
